{
  "scenes": {
    "forest": {
      "entries": [
        "berry_thicket",
        "standing_stone"
      ],
      "forage_rate": 0.5
    },
    "plains": {
      "entries": [
        "foraging_oasis",
        "mirage_lure"
      ],
      "forage_rate": 0.5
    }
  },
  "entries": {
    "berry_thicket": {
      "herb": "soothing_mint",
      "text": {
        "spring": "Mint sparkles under dew.",
        "summer": "Thicket hums with bees."
      }
    },
    "standing_stone": {
      "rune_meditation": true,
      "text": {
        "any": "Carved spirals warm to touch."
      }
    },
    "foraging_oasis": {
      "herb": "drought_root",
      "text": {
        "any": "A trickle feeds hardy reeds."
      }
    },
    "mirage_lure": {
      "text": {
        "any": "Heat haze dances with spirit silhouettes."
      }
    }
  }
}